default.toml
pi_hole_influx/__init__.py
pi_hole_influx/__main__.py
pi_hole_influx-0.1.0a1.dist-info/entry_points.txt
pi_hole_influx-0.1.0a1.dist-info/LICENSE
pi_hole_influx-0.1.0a1.dist-info/WHEEL
pi_hole_influx-0.1.0a1.dist-info/METADATA
pi_hole_influx-0.1.0a1.dist-info/RECORD
