Metadata-Version: 2.1
Name: pi-hole-influx
Version: 0.1.0a1
Summary: A python daemon to send Pi-Hole stats for Grafana to InfluxDB
License: Apache-2.0
Author: Jan Willhaus
Author-email: mail@janwillhaus.de
Requires-Python: >=3.5,<4.0
Classifier: License :: OSI Approved :: Apache Software License
Classifier: Programming Language :: Python :: 3
Classifier: Programming Language :: Python :: 3.5
Classifier: Programming Language :: Python :: 3.6
Classifier: Programming Language :: Python :: 3.7
Classifier: Programming Language :: Python :: 3.8
Requires-Dist: dynaconf (>=2.2.2,<3.0.0)
Requires-Dist: influxdb (>=5.2.3,<6.0.0)
Requires-Dist: sdnotify (>=0.3.2,<0.4.0)
